knmi_dataset_downloader/__init__.py
knmi_dataset_downloader/api_key.py
knmi_dataset_downloader/cli.py
knmi_dataset_downloader/dataset.py
knmi_dataset_downloader/defaults.py
knmi_dataset_downloader/knmi_dataset_api/api_client.py
knmi_dataset_downloader/knmi_dataset_api/kiota-lock.json
knmi_dataset_downloader/knmi_dataset_api/models/file_download.py
knmi_dataset_downloader/knmi_dataset_api/models/file_summary.py
knmi_dataset_downloader/knmi_dataset_api/models/list_files_response.py
knmi_dataset_downloader/knmi_dataset_api/v1/v1_request_builder.py
knmi_dataset_downloader/knmi_dataset_api/v1/datasets/datasets_request_builder.py
knmi_dataset_downloader/knmi_dataset_api/v1/datasets/item/with_dataset_name_item_request_builder.py
knmi_dataset_downloader/knmi_dataset_api/v1/datasets/item/versions/versions_request_builder.py
knmi_dataset_downloader/knmi_dataset_api/v1/datasets/item/versions/item/with_version_item_request_builder.py
knmi_dataset_downloader/knmi_dataset_api/v1/datasets/item/versions/item/files/files_request_builder.py
knmi_dataset_downloader/knmi_dataset_api/v1/datasets/item/versions/item/files/get_order_by_query_parameter_type.py
knmi_dataset_downloader/knmi_dataset_api/v1/datasets/item/versions/item/files/get_sorting_query_parameter_type.py
knmi_dataset_downloader/knmi_dataset_api/v1/datasets/item/versions/item/files/item/with_filename_item_request_builder.py
knmi_dataset_downloader/knmi_dataset_api/v1/datasets/item/versions/item/files/item/url/url_request_builder.py
knmi_dataset_downloader-1.8.0.dist-info/METADATA
knmi_dataset_downloader-1.8.0.dist-info/WHEEL
knmi_dataset_downloader-1.8.0.dist-info/entry_points.txt
knmi_dataset_downloader-1.8.0.dist-info/licenses/LICENSE
knmi_dataset_downloader-1.8.0.dist-info/RECORD
