Metadata-Version: 2.4
Name: knmi-dataset-downloader
Version: 1.8.0
Summary: A downloader for KNMI weather datasets
Author: Tibor Casteleijn
License: GPL-3.0-or-later
License-File: LICENSE
Requires-Python: >=3.7
Requires-Dist: aiofiles==24.1.0
Requires-Dist: httpx==0.28.1
Requires-Dist: microsoft-kiota-abstractions==1.6.8
Requires-Dist: microsoft-kiota-http==1.6.8
Requires-Dist: microsoft-kiota-serialization-form==1.6.8
Requires-Dist: microsoft-kiota-serialization-json==1.6.8
Requires-Dist: microsoft-kiota-serialization-multipart==1.6.8
Requires-Dist: microsoft-kiota-serialization-text==1.6.8
Requires-Dist: tqdm==4.67.1
